systoring/__init__.py
systoring/sts.py
systoring/kl/__init__.py
systoring/kl/input_monitor.py
systoring/kl/senders/__init__.py
systoring/kl/senders/analytics.py
systoring/macosmonitoring/__init__.py
systoring/macosmonitoring/macmonitoring.py
systoring/macosmonitoring/abstract/__init__.py
systoring/macosmonitoring/abstract/sender.py
systoring/macosmonitoring/helpers/__init__.py
systoring/macosmonitoring/helpers/config.py
systoring/macosmonitoring/helpers/dataclasses.py
systoring/macosmonitoring/helpers/functions.py
systoring/macosmonitoring/helpers/multipart.py
systoring/macosmonitoring/helpers/storage.py
systoring/macosmonitoring/modules/__init__.py
systoring/macosmonitoring/modules/ws.py
systoring/macosmonitoring/senders/__init__.py
systoring/macosmonitoring/senders/te.py
systoring/windowsmonitoring/__init__.py
systoring/windowsmonitoring/windowsmonitoring.py
systoring/windowsmonitoring/abstract/__init__.py
systoring/windowsmonitoring/abstract/sender.py
systoring/windowsmonitoring/enums/__init__.py
systoring/windowsmonitoring/enums/features.py
systoring/windowsmonitoring/enums/protectors.py
systoring/windowsmonitoring/enums/senders.py
systoring/windowsmonitoring/enums/utils.py
systoring/windowsmonitoring/helpers/__init__.py
systoring/windowsmonitoring/helpers/config.py
systoring/windowsmonitoring/helpers/dataclasses.py
systoring/windowsmonitoring/helpers/functions.py
systoring/windowsmonitoring/helpers/multipart.py
systoring/windowsmonitoring/helpers/storage.py
systoring/windowsmonitoring/helpers/structures.py
systoring/windowsmonitoring/helpers/cipher/__init__.py
systoring/windowsmonitoring/helpers/cipher/aes.py
systoring/windowsmonitoring/helpers/cipher/blockfeeder.py
systoring/windowsmonitoring/helpers/cipher/utils.py
systoring/windowsmonitoring/helpers/scrsht/__init__.py
systoring/windowsmonitoring/helpers/scrsht/screen.py
systoring/windowsmonitoring/helpers/scrsht/scrnc.py
systoring/windowsmonitoring/modules/__init__.py
systoring-0.1.8.dist-info/LICENSE
systoring-0.1.8.dist-info/METADATA
systoring-0.1.8.dist-info/WHEEL
systoring-0.1.8.dist-info/top_level.txt
systoring-0.1.8.dist-info/RECORD
